caos/__init__.py
caos/_cli.py
caos/_cli_commands/__init__.py
caos/_cli_commands/help_command.py
caos/_cli_commands/raise_exceptions.py
caos/_cli_commands/version_command.py
caos/_cli_commands/command_check/__init__.py
caos/_cli_commands/command_check/src/__init__.py
caos/_cli_commands/command_check/src/constants.py
caos/_cli_commands/command_check/src/entry_point.py
caos/_cli_commands/command_init/__init__.py
caos/_cli_commands/command_init/src/__init__.py
caos/_cli_commands/command_init/src/constants.py
caos/_cli_commands/command_init/src/entry_point.py
caos/_cli_commands/command_init/src/exceptions.py
caos/_cli_commands/command_pip/__init__.py
caos/_cli_commands/command_pip/src/__init__.py
caos/_cli_commands/command_pip/src/constants.py
caos/_cli_commands/command_pip/src/entry_point.py
caos/_cli_commands/command_python/__init__.py
caos/_cli_commands/command_python/src/__init__.py
caos/_cli_commands/command_python/src/constants.py
caos/_cli_commands/command_python/src/entry_point.py
caos/_cli_commands/command_run/__init__.py
caos/_cli_commands/command_run/src/__init__.py
caos/_cli_commands/command_run/src/constants.py
caos/_cli_commands/command_run/src/entry_point.py
caos/_cli_commands/command_run/src/exceptions.py
caos/_cli_commands/command_update/__init__.py
caos/_cli_commands/command_update/src/__init__.py
caos/_cli_commands/command_update/src/constants.py
caos/_cli_commands/command_update/src/entry_point.py
caos/_internal/__init__.py
caos/_internal/constants.py
caos/_internal/exceptions.py
caos/_internal/types.py
caos/_internal/console/__init__.py
caos/_internal/console/ansi_colors.py
caos/_internal/console/console_art.py
caos/_internal/console/tools.py
caos/_internal/utils/__init__.py
caos/_internal/utils/commands.py
caos/_internal/utils/dependencies.py
caos/_internal/utils/os.py
caos/_internal/utils/working_directory.py
caos/_internal/utils/yaml.py
caos/_third_party/__init__.py
caos/_third_party/colorama_0_4_3/LICENSE
caos/_third_party/colorama_0_4_3/README
caos-3.0.1.dist-info/AUTHORS.txt
caos-3.0.1.dist-info/LICENSE
caos-3.0.1.dist-info/METADATA
caos-3.0.1.dist-info/WHEEL
caos-3.0.1.dist-info/entry_points.txt
caos-3.0.1.dist-info/top_level.txt
caos-3.0.1.dist-info/RECORD
