Metadata-Version: 2.1
Name: caos
Version: 3.0.1
Summary: A simple dependency management tool and tasks executor for Python projects
Home-page: https://github.com/caotic-co/caos/
Author: Camilo Ospina
Author-email: camilo.ospinaa@gmail.com
Keywords: caos virtualenv dependencies manager poetry pip-tools npm pnpm bun maven composer pipenv venv easy_install setuptools wheel
Platform: Windows
Platform: Linux
Platform: Mac OS-X
Platform: Unix
Classifier: Intended Audience :: Developers
Classifier: Programming Language :: Python :: 3.6
Classifier: Programming Language :: Python :: 3.7
Classifier: Programming Language :: Python :: 3.8
Classifier: Programming Language :: Python :: 3.9
Classifier: Programming Language :: Python :: 3.10
Classifier: Programming Language :: Python :: 3.11
Classifier: Programming Language :: Python :: 3.12
Classifier: License :: OSI Approved :: Apache Software License
Classifier: Operating System :: OS Independent
Classifier: Programming Language :: Python :: Implementation :: CPython
Classifier: Programming Language :: Python :: Implementation :: PyPy
Classifier: Operating System :: Microsoft :: Windows
Classifier: Operating System :: POSIX
Classifier: Operating System :: Unix
Classifier: Operating System :: MacOS
Requires-Python: >=3.6
License-File: LICENSE
License-File: AUTHORS.txt
Requires-Dist: pip >=9.0.0
Requires-Dist: virtualenv >=16.0.0
